{
  "DataSources": [
    {
      "Name": "CustomGallerySample",
      "Schema": "*[SampleHeading:s, SampleImage:i, SampleText:s]",
      "IsSampleData": true,
      "IsWritable": false,
      "Type": "StaticDataSourceInfo",
      "OriginalSchema": "*[SampleHeading:s, SampleImage:i, SampleText:s]",
      "Data": "[{\"SampleHeading\":\"Lorem ipsum 1\",\"SampleImage\":\"/ctrllib/image/images/SampleImage.svg\",\"SampleText\":\"Lorem ipsum dolor sit amet, consectetur adipiscing elit.\"},{\"SampleHeading\":\"Lorem ipsum 2\",\"SampleImage\":\"/ctrllib/image/images/SampleImage.svg\",\"SampleText\":\"Suspendisse enim metus, tincidunt quis lobortis a, fringilla dignissim neque.\"},{\"SampleHeading\":\"Lorem ipsum 3\",\"SampleImage\":\"/ctrllib/image/images/SampleImage.svg\",\"SampleText\":\"Ut pharetra a dolor ac vehicula.\"},{\"SampleHeading\":\"Lorem ipsum 4\",\"SampleImage\":\"/ctrllib/image/images/SampleImage.svg\",\"SampleText\":\"Vestibulum dui felis, fringilla nec mi sed, tristique dictum nisi.\"}]",
      "OriginalName": "CustomGallerySample",
      "OrderedColumnNames": [
        "SampleImage",
        "SampleHeading",
        "SampleText"
      ]
    },
    {
      "Name": "Suyog Financial Performance",
      "IsSampleData": false,
      "IsWritable": true,
      "Type": "ConnectedDataSourceInfo",
      "DatasetName": "https://codeneraprivatelimited-my.sharepoint.com/personal/ashutoshupadhyay_codeneraprivatelimited_onmicrosoft_com",
      "TableName": "e779dc0e-3c16-4d9e-b409-377f8a47598e",
      "ApiId": "/providers/microsoft.powerapps/apis/shared_sharepointonline",
      "EncodeDataset": true,
      "CdpRevision": {
        "RevisionNumber": 1,
        "BaseUrl": "/",
        "LastChangedTimeString": "2024-02-08T17:53:32.2760000Z"
      },
      "DataEntityMetadataJson": {
        "e779dc0e-3c16-4d9e-b409-377f8a47598e": "{\"name\":\"e779dc0e-3c16-4d9e-b409-377f8a47598e\",\"title\":\"Suyog Financial Performance\",\"x-ms-permission\":\"read-write\",\"x-ms-capabilities\":{\"sortRestrictions\":{\"sortable\":true,\"unsortableProperties\":[\"{Identifier}\",\"{IsFolder}\",\"{Thumbnail}\",\"{Link}\",\"{Name}\",\"{FilenameWithExtension}\",\"{Path}\",\"{FullPath}\",\"{ModerationStatus}\",\"{ModerationComment}\",\"{HasAttachments}\",\"{Attachments}\",\"{VersionNumber}\",\"{TriggerWindowStartToken}\",\"{TriggerWindowEndToken}\"]},\"filterRestrictions\":{\"filterable\":true,\"nonFilterableProperties\":[\"{Identifier}\",\"{IsFolder}\",\"{Thumbnail}\",\"{Link}\",\"{Name}\",\"{FilenameWithExtension}\",\"{Path}\",\"{FullPath}\",\"{ModerationStatus}\",\"{ModerationComment}\",\"{HasAttachments}\",\"{Attachments}\",\"{VersionNumber}\",\"{TriggerWindowStartToken}\",\"{TriggerWindowEndToken}\"]},\"isOnlyServerPagable\":true,\"filterFunctionSupport\":[\"and\",\"or\",\"eq\",\"startswith\",\"gt\",\"ge\",\"lt\",\"le\",\"ne\"],\"serverPagingOptions\":[\"top\",\"skiptoken\"],\"odataVersion\":3},\"schema\":{\"type\":\"array\",\"items\":{\"type\":\"object\",\"required\":[],\"properties\":{\"ID\":{\"title\":\"ID\",\"description\":\"List item id. Use this value for specifying the item to act on in other list related actions.\",\"type\":\"integer\",\"format\":\"int64\",\"x-ms-keyType\":\"primary\",\"x-ms-keyOrder\":1,\"x-ms-permission\":\"read-only\",\"x-ms-sort\":\"asc,desc\",\"x-ms-capabilities\":{\"filterFunctions\":[\"eq\"]}},\"Title\":{\"title\":\"Title\",\"type\":\"string\",\"x-ms-permission\":\"read-write\",\"x-ms-sort\":\"asc,desc\",\"x-ms-capabilities\":{\"filterFunctions\":[\"eq\",\"startswith\"]},\"maxLength\":255},\"Country\":{\"title\":\"Country\",\"type\":\"string\",\"x-ms-permission\":\"read-write\",\"x-ms-sort\":\"asc,desc\",\"x-ms-capabilities\":{\"filterFunctions\":[\"eq\",\"startswith\"]},\"maxLength\":255},\"SalesReps\":{\"title\":\"Sales Reps\",\"type\":\"string\",\"x-ms-permission\":\"read-write\",\"x-ms-sort\":\"asc,desc\",\"x-ms-capabilities\":{\"filterFunctions\":[\"eq\",\"startswith\"]},\"maxLength\":255},\"FirstName\":{\"title\":\"First Name\",\"type\":\"string\",\"x-ms-permission\":\"read-write\",\"x-ms-sort\":\"asc,desc\",\"x-ms-capabilities\":{\"filterFunctions\":[\"eq\",\"startswith\"]},\"maxLength\":255},\"LastName\":{\"title\":\"Last Name\",\"type\":\"string\",\"x-ms-permission\":\"read-write\",\"x-ms-sort\":\"asc,desc\",\"x-ms-capabilities\":{\"filterFunctions\":[\"eq\",\"startswith\"]},\"maxLength\":255},\"Gender\":{\"title\":\"Gender\",\"type\":\"string\",\"x-ms-permission\":\"read-write\",\"x-ms-sort\":\"asc,desc\",\"x-ms-capabilities\":{\"filterFunctions\":[\"eq\",\"startswith\"]},\"maxLength\":255},\"Age\":{\"title\":\"Age\",\"type\":\"number\",\"format\":\"double\",\"x-ms-permission\":\"read-write\",\"x-ms-sort\":\"asc,desc\",\"x-ms-capabilities\":{\"filterFunctions\":[\"eq\",\"gt\",\"ge\",\"lt\",\"le\",\"ne\"]},\"maximum\":1.7976931348623157e+308,\"minimum\":-1.7976931348623157e+308},\"RankLevels\":{\"title\":\"Rank Levels\",\"type\":\"string\",\"x-ms-permission\":\"read-write\",\"x-ms-sort\":\"asc,desc\",\"x-ms-capabilities\":{\"filterFunctions\":[\"eq\",\"startswith\"]},\"maxLength\":255},\"Rank\":{\"title\":\"Rank\",\"type\":\"string\",\"x-ms-permission\":\"read-write\",\"x-ms-sort\":\"asc,desc\",\"x-ms-capabilities\":{\"filterFunctions\":[\"eq\",\"startswith\"]},\"maxLength\":255},\"Products\":{\"title\":\"Products\",\"type\":\"string\",\"x-ms-permission\":\"read-write\",\"x-ms-sort\":\"asc,desc\",\"x-ms-capabilities\":{\"filterFunctions\":[\"eq\",\"startswith\"]},\"maxLength\":255},\"Years\":{\"title\":\"Years\",\"type\":\"number\",\"format\":\"double\",\"x-ms-permission\":\"read-write\",\"x-ms-sort\":\"asc,desc\",\"x-ms-capabilities\":{\"filterFunctions\":[\"eq\",\"gt\",\"ge\",\"lt\",\"le\",\"ne\"]},\"maximum\":1.7976931348623157e+308,\"minimum\":-1.7976931348623157e+308},\"Quarter\":{\"title\":\"Quarter\",\"type\":\"string\",\"x-ms-permission\":\"read-write\",\"x-ms-sort\":\"asc,desc\",\"x-ms-capabilities\":{\"filterFunctions\":[\"eq\",\"startswith\"]},\"maxLength\":255},\"Month\":{\"title\":\"Month\",\"type\":\"number\",\"format\":\"double\",\"x-ms-permission\":\"read-write\",\"x-ms-sort\":\"asc,desc\",\"x-ms-capabilities\":{\"filterFunctions\":[\"eq\",\"gt\",\"ge\",\"lt\",\"le\",\"ne\"]},\"maximum\":1.7976931348623157e+308,\"minimum\":-1.7976931348623157e+308},\"Revenue_x0028_USD_x0029_\":{\"title\":\"Revenue (USD)\",\"type\":\"number\",\"format\":\"double\",\"x-ms-permission\":\"read-write\",\"x-ms-sort\":\"asc,desc\",\"x-ms-capabilities\":{\"filterFunctions\":[\"eq\",\"gt\",\"ge\",\"lt\",\"le\",\"ne\"]},\"maximum\":1.7976931348623157e+308,\"minimum\":-1.7976931348623157e+308},\"OData__ColorTag\":{\"title\":\"Color Tag\",\"type\":\"string\",\"x-ms-permission\":\"read-only\",\"x-ms-sort\":\"asc,desc\",\"x-ms-capabilities\":{\"filterFunctions\":[\"eq\",\"startswith\"]},\"maxLength\":255},\"ComplianceAssetId\":{\"title\":\"Compliance Asset Id\",\"type\":\"string\",\"x-ms-permission\":\"read-only\",\"x-ms-sort\":\"asc,desc\",\"x-ms-capabilities\":{\"filterFunctions\":[\"eq\",\"startswith\"]},\"maxLength\":255},\"Modified\":{\"title\":\"Modified\",\"description\":\"When this item was last changed.\",\"type\":\"string\",\"format\":\"date-time\",\"x-ms-permission\":\"read-only\",\"x-ms-sort\":\"asc,desc\",\"x-ms-capabilities\":{\"filterFunctions\":[\"eq\",\"gt\",\"ge\",\"lt\",\"le\",\"ne\"]}},\"Created\":{\"title\":\"Created\",\"description\":\"When this item was created.\",\"type\":\"string\",\"format\":\"date-time\",\"x-ms-permission\":\"read-only\",\"x-ms-sort\":\"asc,desc\",\"x-ms-capabilities\":{\"filterFunctions\":[\"eq\",\"gt\",\"ge\",\"lt\",\"le\",\"ne\"]}},\"Author#Claims\":{\"title\":\"Created By Claims\",\"type\":\"string\",\"description\":\"Internal identifier for the user who created this item.\",\"x-ms-permission\":\"read-only\",\"x-ms-visibility\":\"internal\"},\"Author\":{\"title\":\"Created By\",\"description\":\"The user who created this item.\",\"type\":\"object\",\"x-ms-permission\":\"read-only\",\"x-ms-sort\":\"asc,desc\",\"x-ms-capabilities\":{\"filterFunctions\":[\"eq\"]},\"properties\":{\"@odata.type\":{\"title\":\"@odata.type\",\"x-ms-visibility\":\"internal\",\"type\":\"string\",\"x-ms-permission\":\"read-only\"},\"Claims\":{\"title\":\"Claims\",\"type\":\"string\",\"description\":\"Internal identifier for the user who created this item.\",\"x-ms-permission\":\"read-only\",\"x-ms-dynamic-values\":{\"operationId\":\"GetEntityValues\",\"parameters\":{\"dataset\":{\"parameter\":\"dataset\"},\"table\":{\"parameter\":\"table\"},\"id\":\"1df5e554-ec7e-46a6-901d-d85a3881cb18\"},\"value-path\":\"Claims\",\"value-title\":\"DisplayName\",\"value-collection\":\"value\"}},\"DisplayName\":{\"title\":\"DisplayName\",\"type\":\"string\",\"description\":\"The name of the user who created this item.\",\"x-ms-permission\":\"read-only\",\"x-ms-capabilities\":{\"x-ms-sp\":{\"OdataQueryName\":\"Title\"},\"filterFunctions\":[\"eq\",\"startswith\"]}},\"Email\":{\"title\":\"Email\",\"type\":\"string\",\"description\":\"Email address of the user who created this item.\",\"format\":\"email\",\"x-ms-permission\":\"read-only\",\"x-ms-capabilities\":{\"x-ms-sp\":{\"OdataQueryName\":\"EMail\"},\"filterFunctions\":[\"eq\",\"startswith\"]}},\"Picture\":{\"title\":\"Picture\",\"type\":\"string\",\"description\":\"Link to a picture of the user who created this item.\",\"format\":\"uri\",\"x-ms-media-kind\":\"image\",\"x-ms-media-default-folder-path\":\"/personal/ashutoshupadhyay_codeneraprivatelimited_onmicrosoft_com\",\"x-ms-media-base-url\":\"https://codeneraprivatelimited-my.sharepoint.com/personal/ashutoshupadhyay_codeneraprivatelimited_onmicrosoft_com\",\"x-ms-permission\":\"read-only\"},\"Department\":{\"title\":\"Department\",\"type\":\"string\",\"description\":\"Department name of the user who created this item.\",\"x-ms-permission\":\"read-only\"},\"JobTitle\":{\"title\":\"JobTitle\",\"type\":\"string\",\"description\":\"Job title of the user who created this item.\",\"x-ms-permission\":\"read-only\"}},\"x-ms-displayFormat\":{\"titleProperty\":\"DisplayName\",\"subtitleProperty\":\"Email\",\"thumbnailProperty\":\"Picture\"}},\"Editor#Claims\":{\"title\":\"Modified By Claims\",\"type\":\"string\",\"description\":\"Internal identifier for the user who last changed this item.\",\"x-ms-permission\":\"read-only\",\"x-ms-visibility\":\"internal\"},\"Editor\":{\"title\":\"Modified By\",\"description\":\"The user who last changed this item.\",\"type\":\"object\",\"x-ms-permission\":\"read-only\",\"x-ms-sort\":\"asc,desc\",\"x-ms-capabilities\":{\"filterFunctions\":[\"eq\"]},\"properties\":{\"@odata.type\":{\"title\":\"@odata.type\",\"x-ms-visibility\":\"internal\",\"type\":\"string\",\"x-ms-permission\":\"read-only\"},\"Claims\":{\"title\":\"Claims\",\"type\":\"string\",\"description\":\"Internal identifier for the user who last changed this item.\",\"x-ms-permission\":\"read-only\",\"x-ms-dynamic-values\":{\"operationId\":\"GetEntityValues\",\"parameters\":{\"dataset\":{\"parameter\":\"dataset\"},\"table\":{\"parameter\":\"table\"},\"id\":\"d31655d1-1d5b-4511-95a1-7a09e9b75bf2\"},\"value-path\":\"Claims\",\"value-title\":\"DisplayName\",\"value-collection\":\"value\"}},\"DisplayName\":{\"title\":\"DisplayName\",\"type\":\"string\",\"description\":\"The name of the user who last changed this item.\",\"x-ms-permission\":\"read-only\",\"x-ms-capabilities\":{\"x-ms-sp\":{\"OdataQueryName\":\"Title\"},\"filterFunctions\":[\"eq\",\"startswith\"]}},\"Email\":{\"title\":\"Email\",\"type\":\"string\",\"description\":\"Email address of the user who last changed this item.\",\"format\":\"email\",\"x-ms-permission\":\"read-only\",\"x-ms-capabilities\":{\"x-ms-sp\":{\"OdataQueryName\":\"EMail\"},\"filterFunctions\":[\"eq\",\"startswith\"]}},\"Picture\":{\"title\":\"Picture\",\"type\":\"string\",\"description\":\"Link to a picture of the user who last changed this item.\",\"format\":\"uri\",\"x-ms-media-kind\":\"image\",\"x-ms-media-default-folder-path\":\"/personal/ashutoshupadhyay_codeneraprivatelimited_onmicrosoft_com\",\"x-ms-media-base-url\":\"https://codeneraprivatelimited-my.sharepoint.com/personal/ashutoshupadhyay_codeneraprivatelimited_onmicrosoft_com\",\"x-ms-permission\":\"read-only\"},\"Department\":{\"title\":\"Department\",\"type\":\"string\",\"description\":\"Department name of the user who last changed this item.\",\"x-ms-permission\":\"read-only\"},\"JobTitle\":{\"title\":\"JobTitle\",\"type\":\"string\",\"description\":\"Job title of the user who last changed this item.\",\"x-ms-permission\":\"read-only\"}},\"x-ms-displayFormat\":{\"titleProperty\":\"DisplayName\",\"subtitleProperty\":\"Email\",\"thumbnailProperty\":\"Picture\"}},\"{Identifier}\":{\"title\":\"Identifier\",\"description\":\"Value that can be used in file related actions for selecting a file.\",\"type\":\"string\",\"x-ms-permission\":\"read-only\",\"x-ms-sort\":\"none\"},\"{IsFolder}\":{\"title\":\"IsFolder\",\"description\":\"True when the item is a folder, false otherwise.\",\"type\":\"boolean\",\"x-ms-permission\":\"read-only\",\"x-ms-sort\":\"none\"},\"{Thumbnail}\":{\"title\":\"Thumbnail\",\"description\":\"URL to the thumbnails of the item in 3 different sizes, if available.\",\"type\":\"object\",\"x-ms-permission\":\"read-only\",\"x-ms-sort\":\"none\",\"properties\":{\"@odata.type\":{\"title\":\"@odata.type\",\"x-ms-visibility\":\"internal\",\"type\":\"string\",\"x-ms-permission\":\"read-only\"},\"Small\":{\"title\":\"Small\",\"type\":\"string\",\"description\":\"URL to the small, highly compressed size thumbnail of the item, if available.\",\"x-ms-permission\":\"read-only\"},\"Medium\":{\"title\":\"Medium\",\"type\":\"string\",\"description\":\"URL to the standard size thumbnail of the item, if available.\",\"x-ms-permission\":\"read-only\"},\"Large\":{\"title\":\"Large\",\"type\":\"string\",\"description\":\"URL to the largest size thumbnail of the item, if available.\",\"x-ms-permission\":\"read-only\"}}},\"{Link}\":{\"title\":\"Link to item\",\"description\":\"Link that can be used to get to the file or list item. Only people with permissions to the item will be able to open the link.\",\"type\":\"string\",\"x-ms-permission\":\"read-only\",\"x-ms-sort\":\"none\"},\"{Name}\":{\"title\":\"Name\",\"description\":\"File name of the item in document libraries, display name of the item in lists.\",\"type\":\"string\",\"x-ms-permission\":\"read-only\",\"x-ms-sort\":\"none\"},\"{FilenameWithExtension}\":{\"title\":\"File name with extension\",\"description\":\"For libraries, returns file name including extension. For lists, returns the title property.\",\"type\":\"string\",\"x-ms-permission\":\"read-only\",\"x-ms-sort\":\"none\"},\"{Path}\":{\"title\":\"Folder path\",\"description\":\"Path to the folder the item is in, relative to the site address.\",\"type\":\"string\",\"x-ms-permission\":\"read-only\",\"x-ms-sort\":\"none\"},\"{FullPath}\":{\"title\":\"Full Path\",\"description\":\"Full path of an item or a folder or a file\",\"type\":\"string\",\"x-ms-permission\":\"read-only\",\"x-ms-sort\":\"none\"},\"{ModerationStatus}\":{\"title\":\"Content approval status\",\"description\":\"The content approval status. It can be one of the following: Draft, Pending, Approved, or Rejected\",\"type\":\"string\",\"x-ms-permission\":\"read-only\",\"x-ms-sort\":\"none\"},\"{ModerationComment}\":{\"title\":\"Comments associated with the content approval of this list item\",\"description\":\"The comments associated with moderation of the list item.\",\"type\":\"string\",\"x-ms-permission\":\"read-only\",\"x-ms-sort\":\"none\"},\"{HasAttachments}\":{\"title\":\"Has attachments\",\"description\":\"Indicates the presence of attachments in the item.\",\"type\":\"boolean\",\"x-ms-permission\":\"read-only\",\"x-ms-sort\":\"none\"},\"{Attachments}@odata.type\":{\"title\":\"{Attachments}\",\"type\":\"string\",\"x-ms-visibility\":\"internal\",\"x-ms-permission\":\"read-write\"},\"{Attachments}\":{\"title\":\"Attachments\",\"description\":\"Never returns any data. Use Attachment endpoints to access item attachments.\",\"x-ms-permission\":\"read-write\",\"targetEntity\":\"attachments\",\"format\":\"x-ms-containedMediaEntity\",\"x-ms-visibility\":\"internal\",\"type\":\"array\",\"items\":{\"type\":\"object\",\"format\":\"x-ms-mediaEntity\",\"x-ms-sort\":\"none\",\"properties\":{\"@odata.type\":{\"title\":\"@odata.type\",\"x-ms-visibility\":\"internal\",\"type\":\"string\",\"x-ms-permission\":\"read-write\"},\"Id\":{\"title\":\"Id\",\"type\":\"string\",\"x-ms-keyType\":\"primary\",\"x-ms-keyOrder\":1,\"x-ms-permission\":\"read-only\"},\"AbsoluteUri\":{\"title\":\"AbsoluteUri\",\"type\":\"string\",\"format\":\"uri\",\"x-ms-permission\":\"read-only\"},\"DisplayName\":{\"title\":\"DisplayName\",\"type\":\"string\",\"x-ms-permission\":\"read-only\"}}},\"@odata.type\":\"#Collection(Microsoft.Azure.Connectors.SharePoint.SPListItemAttachment)\"},\"{VersionNumber}\":{\"title\":\"Version number\",\"description\":\"The version number of the file or the list item.\",\"type\":\"string\",\"x-ms-permission\":\"read-only\",\"x-ms-sort\":\"none\"},\"{TriggerWindowStartToken}\":{\"title\":\"Trigger Window Start Token\",\"description\":\"A token expressing the time of the last flow check. Use this if you want to check if one or more columns were modified since the last flow check.\",\"type\":\"string\",\"x-ms-permission\":\"read-only\",\"x-ms-sort\":\"none\"},\"{TriggerWindowEndToken}\":{\"title\":\"Trigger Window End Token\",\"description\":\"A token expressing the time of the current flow check. Use this if you want to check if one or more columns were modified since the last flow check.\",\"type\":\"string\",\"x-ms-permission\":\"read-only\",\"x-ms-sort\":\"none\"}},\"x-ms-relationships\":{\"Author\":{\"targetEntity\":\"Author\",\"referentialConstraints\":{\"Author#Claims\":{\"referencedProperty\":\"Claims\"}}},\"Editor\":{\"targetEntity\":\"Editor\",\"referentialConstraints\":{\"Editor#Claims\":{\"referencedProperty\":\"Claims\"}}}},\"x-ms-displayFormat\":{\"propertiesDisplayOrder\":[\"Title\",\"Country\",\"SalesReps\",\"FirstName\",\"LastName\",\"Gender\",\"Age\",\"RankLevels\",\"Rank\",\"Products\",\"Years\",\"Quarter\",\"Month\",\"Revenue_x0028_USD_x0029_\",\"{Attachments}\"],\"propertiesCompactDisplayOrder\":[\"Title\",\"Country\",\"SalesReps\",\"FirstName\",\"LastName\",\"Gender\",\"Age\",\"RankLevels\",\"Rank\",\"Products\",\"Years\",\"Quarter\",\"Month\",\"Revenue_x0028_USD_x0029_\"],\"propertiesTabularDisplayOrder\":[\"Title\",\"Country\",\"SalesReps\",\"FirstName\",\"LastName\",\"Gender\",\"Age\",\"RankLevels\",\"Rank\",\"Products\",\"Years\",\"Quarter\",\"Month\",\"Revenue_x0028_USD_x0029_\"]}}},\"referencedEntities\":{\"Author\":{\"lookupEndpoint\":{\"path\":\"/tables/e779dc0e-3c16-4d9e-b409-377f8a47598e/entities/Author\",\"capabilities\":{\"searchable\":true,\"requiresSearch\":false}}},\"Editor\":{\"lookupEndpoint\":{\"path\":\"/tables/e779dc0e-3c16-4d9e-b409-377f8a47598e/entities/Editor\",\"capabilities\":{\"searchable\":true,\"requiresSearch\":false}}}},\"webUrl\":\"https://codeneraprivatelimited-my.sharepoint.com/personal/ashutoshupadhyay_codeneraprivatelimited_onmicrosoft_com/Lists/Suyog Financial Performance/AllItems.aspx\"}"
      },
      "ConnectedDataSourceInfoNameMapping": {
        "Title": "Title",
        "SalesReps": "Sales Reps",
        "Gender": "Gender",
        "{TriggerWindowEndToken}": "Trigger Window End Token",
        "Month": "Month",
        "{Link}": "Link to item",
        "LastName": "Last Name",
        "ComplianceAssetId": "Compliance Asset Id",
        "Editor": "Modified By",
        "{Attachments}@odata.type": "{Attachments} ({Attachments}@odata.type)",
        "FirstName": "First Name",
        "Editor#Claims": "Modified By Claims",
        "{IsFolder}": "IsFolder",
        "{VersionNumber}": "Version number",
        "Products": "Products",
        "Rank": "Rank",
        "{Thumbnail}": "Thumbnail",
        "{Path}": "Folder path",
        "{FilenameWithExtension}": "File name with extension",
        "{ModerationStatus}": "Content approval status",
        "RankLevels": "Rank Levels",
        "Quarter": "Quarter",
        "{Identifier}": "Identifier",
        "OData__ColorTag": "Color Tag",
        "Author": "Created By",
        "{FullPath}": "Full Path",
        "Age": "Age",
        "{Attachments}": "Attachments",
        "{HasAttachments}": "Has attachments",
        "Revenue_x0028_USD_x0029_": "Revenue (USD)",
        "Author#Claims": "Created By Claims",
        "Created": "Created",
        "ID": "ID",
        "{ModerationComment}": "Comments associated with the content approval of this list item",
        "Years": "Years",
        "Country": "Country",
        "Modified": "Modified",
        "{TriggerWindowStartToken}": "Trigger Window Start Token",
        "{Name}": "Name"
      }
    },
    {
      "Name": "DropDownSample",
      "Schema": "*[Value:s]",
      "IsSampleData": true,
      "IsWritable": false,
      "Type": "StaticDataSourceInfo",
      "OriginalSchema": "*[Value:s]",
      "Data": "[{\"Value\":\"1\"},{\"Value\":\"2\"},{\"Value\":\"3\"}]",
      "OriginalName": "DropDownSample",
      "OrderedColumnNames": [
        "Value"
      ]
    },
    {
      "Name": "ColumnChartSample",
      "Schema": "*[Area:n, City:s, Density:n, Population:n]",
      "IsSampleData": true,
      "IsWritable": false,
      "Type": "StaticDataSourceInfo",
      "OriginalSchema": "*[Area:n, City:s, Density:n, Population:n]",
      "Data": "[{\"Area\":31,\"City\":\"Cairo\",\"Density\":39,\"Population\":12},{\"Area\":15,\"City\":\"Delhi\",\"Density\":78,\"Population\":18},{\"Area\":11,\"City\":\"Mexico City\",\"Density\":60,\"Population\":8},{\"Area\":22,\"City\":\"Istanbul\",\"Density\":65,\"Population\":14},{\"Area\":16,\"City\":\"London\",\"Density\":54,\"Population\":8},{\"Area\":25,\"City\":\"Moscow\",\"Density\":48,\"Population\":12},{\"Area\":8,\"City\":\"New York City\",\"Density\":107,\"Population\":8},{\"Area\":6,\"City\":\"Seoul\",\"Density\":172,\"Population\":10},{\"Area\":6,\"City\":\"Shanghai\",\"Density\":38,\"Population\":24},{\"Area\":6,\"City\":\"Tokyo\",\"Density\":146,\"Population\":9}]",
      "OriginalName": "ColumnChartSample",
      "OrderedColumnNames": [
        "City",
        "Population",
        "Area",
        "Density"
      ]
    },
    {
      "Name": "LegendSample",
      "Schema": "*[Value:s]",
      "IsSampleData": true,
      "IsWritable": false,
      "Type": "StaticDataSourceInfo",
      "OriginalSchema": "*[Value:s]",
      "Data": "[{\"Value\":\"Lorem ipsum\"},{\"Value\":\"Dolor sit\"},{\"Value\":\"Amet consectetur \"},{\"Value\":\"Adipisicing elit\"},{\"Value\":\"Sed do\"},{\"Value\":\"Eiusmod tempor \"},{\"Value\":\"Incididunt ut\"}]",
      "OriginalName": "LegendSample",
      "OrderedColumnNames": [
        "Value"
      ]
    },
    {
      "Name": "PieChartSample",
      "Schema": "*[Area:n, City:s, Density:n, Population:n]",
      "IsSampleData": true,
      "IsWritable": false,
      "Type": "StaticDataSourceInfo",
      "OriginalSchema": "*[Area:n, City:s, Density:n, Population:n]",
      "Data": "[{\"Area\":31,\"City\":\"Cairo\",\"Density\":39,\"Population\":12},{\"Area\":15,\"City\":\"Delhi\",\"Density\":78,\"Population\":18},{\"Area\":11,\"City\":\"Mexico City\",\"Density\":60,\"Population\":8},{\"Area\":22,\"City\":\"Istanbul\",\"Density\":65,\"Population\":14},{\"Area\":16,\"City\":\"London\",\"Density\":54,\"Population\":8},{\"Area\":25,\"City\":\"Moscow\",\"Density\":48,\"Population\":12},{\"Area\":8,\"City\":\"New York City\",\"Density\":107,\"Population\":8},{\"Area\":6,\"City\":\"Seoul\",\"Density\":172,\"Population\":10},{\"Area\":6,\"City\":\"Shanghai\",\"Density\":38,\"Population\":24},{\"Area\":6,\"City\":\"Tokyo\",\"Density\":146,\"Population\":9}]",
      "OriginalName": "PieChartSample",
      "OrderedColumnNames": [
        "City",
        "Population",
        "Area",
        "Density"
      ]
    },
    {
      "Name": "Suyog Financial Performance_1",
      "IsSampleData": false,
      "IsWritable": true,
      "Type": "ConnectedDataSourceInfo",
      "DatasetName": "https://codeneraprivatelimited-my.sharepoint.com/personal/ashutoshupadhyay_codeneraprivatelimited_onmicrosoft_com",
      "TableName": "e779dc0e-3c16-4d9e-b409-377f8a47598e",
      "ApiId": "/providers/microsoft.powerapps/apis/shared_sharepointonline",
      "EncodeDataset": true,
      "CdpRevision": {
        "RevisionNumber": 1,
        "BaseUrl": "/",
        "LastChangedTimeString": "2024-02-08T17:53:32.2760000Z"
      },
      "DataEntityMetadataJson": {
        "e779dc0e-3c16-4d9e-b409-377f8a47598e": "{\"name\":\"e779dc0e-3c16-4d9e-b409-377f8a47598e\",\"title\":\"Suyog Financial Performance\",\"x-ms-permission\":\"read-write\",\"x-ms-capabilities\":{\"sortRestrictions\":{\"sortable\":true,\"unsortableProperties\":[\"{Identifier}\",\"{IsFolder}\",\"{Thumbnail}\",\"{Link}\",\"{Name}\",\"{FilenameWithExtension}\",\"{Path}\",\"{FullPath}\",\"{ModerationStatus}\",\"{ModerationComment}\",\"{HasAttachments}\",\"{Attachments}\",\"{VersionNumber}\",\"{TriggerWindowStartToken}\",\"{TriggerWindowEndToken}\"]},\"filterRestrictions\":{\"filterable\":true,\"nonFilterableProperties\":[\"{Identifier}\",\"{IsFolder}\",\"{Thumbnail}\",\"{Link}\",\"{Name}\",\"{FilenameWithExtension}\",\"{Path}\",\"{FullPath}\",\"{ModerationStatus}\",\"{ModerationComment}\",\"{HasAttachments}\",\"{Attachments}\",\"{VersionNumber}\",\"{TriggerWindowStartToken}\",\"{TriggerWindowEndToken}\"]},\"isOnlyServerPagable\":true,\"filterFunctionSupport\":[\"and\",\"or\",\"eq\",\"startswith\",\"gt\",\"ge\",\"lt\",\"le\",\"ne\"],\"serverPagingOptions\":[\"top\",\"skiptoken\"],\"odataVersion\":3},\"schema\":{\"type\":\"array\",\"items\":{\"type\":\"object\",\"required\":[],\"properties\":{\"ID\":{\"title\":\"ID\",\"description\":\"List item id. Use this value for specifying the item to act on in other list related actions.\",\"type\":\"integer\",\"format\":\"int64\",\"x-ms-keyType\":\"primary\",\"x-ms-keyOrder\":1,\"x-ms-permission\":\"read-only\",\"x-ms-sort\":\"asc,desc\",\"x-ms-capabilities\":{\"filterFunctions\":[\"eq\"]}},\"Title\":{\"title\":\"Title\",\"type\":\"string\",\"x-ms-permission\":\"read-write\",\"x-ms-sort\":\"asc,desc\",\"x-ms-capabilities\":{\"filterFunctions\":[\"eq\",\"startswith\"]},\"maxLength\":255},\"Country\":{\"title\":\"Country\",\"type\":\"string\",\"x-ms-permission\":\"read-write\",\"x-ms-sort\":\"asc,desc\",\"x-ms-capabilities\":{\"filterFunctions\":[\"eq\",\"startswith\"]},\"maxLength\":255},\"SalesReps\":{\"title\":\"Sales Reps\",\"type\":\"string\",\"x-ms-permission\":\"read-write\",\"x-ms-sort\":\"asc,desc\",\"x-ms-capabilities\":{\"filterFunctions\":[\"eq\",\"startswith\"]},\"maxLength\":255},\"FirstName\":{\"title\":\"First Name\",\"type\":\"string\",\"x-ms-permission\":\"read-write\",\"x-ms-sort\":\"asc,desc\",\"x-ms-capabilities\":{\"filterFunctions\":[\"eq\",\"startswith\"]},\"maxLength\":255},\"LastName\":{\"title\":\"Last Name\",\"type\":\"string\",\"x-ms-permission\":\"read-write\",\"x-ms-sort\":\"asc,desc\",\"x-ms-capabilities\":{\"filterFunctions\":[\"eq\",\"startswith\"]},\"maxLength\":255},\"Gender\":{\"title\":\"Gender\",\"type\":\"string\",\"x-ms-permission\":\"read-write\",\"x-ms-sort\":\"asc,desc\",\"x-ms-capabilities\":{\"filterFunctions\":[\"eq\",\"startswith\"]},\"maxLength\":255},\"Age\":{\"title\":\"Age\",\"type\":\"number\",\"format\":\"double\",\"x-ms-permission\":\"read-write\",\"x-ms-sort\":\"asc,desc\",\"x-ms-capabilities\":{\"filterFunctions\":[\"eq\",\"gt\",\"ge\",\"lt\",\"le\",\"ne\"]},\"maximum\":1.7976931348623157e+308,\"minimum\":-1.7976931348623157e+308},\"RankLevels\":{\"title\":\"Rank Levels\",\"type\":\"string\",\"x-ms-permission\":\"read-write\",\"x-ms-sort\":\"asc,desc\",\"x-ms-capabilities\":{\"filterFunctions\":[\"eq\",\"startswith\"]},\"maxLength\":255},\"Rank\":{\"title\":\"Rank\",\"type\":\"string\",\"x-ms-permission\":\"read-write\",\"x-ms-sort\":\"asc,desc\",\"x-ms-capabilities\":{\"filterFunctions\":[\"eq\",\"startswith\"]},\"maxLength\":255},\"Products\":{\"title\":\"Products\",\"type\":\"string\",\"x-ms-permission\":\"read-write\",\"x-ms-sort\":\"asc,desc\",\"x-ms-capabilities\":{\"filterFunctions\":[\"eq\",\"startswith\"]},\"maxLength\":255},\"Years\":{\"title\":\"Years\",\"type\":\"number\",\"format\":\"double\",\"x-ms-permission\":\"read-write\",\"x-ms-sort\":\"asc,desc\",\"x-ms-capabilities\":{\"filterFunctions\":[\"eq\",\"gt\",\"ge\",\"lt\",\"le\",\"ne\"]},\"maximum\":1.7976931348623157e+308,\"minimum\":-1.7976931348623157e+308},\"Quarter\":{\"title\":\"Quarter\",\"type\":\"string\",\"x-ms-permission\":\"read-write\",\"x-ms-sort\":\"asc,desc\",\"x-ms-capabilities\":{\"filterFunctions\":[\"eq\",\"startswith\"]},\"maxLength\":255},\"Month\":{\"title\":\"Month\",\"type\":\"number\",\"format\":\"double\",\"x-ms-permission\":\"read-write\",\"x-ms-sort\":\"asc,desc\",\"x-ms-capabilities\":{\"filterFunctions\":[\"eq\",\"gt\",\"ge\",\"lt\",\"le\",\"ne\"]},\"maximum\":1.7976931348623157e+308,\"minimum\":-1.7976931348623157e+308},\"Revenue_x0028_USD_x0029_\":{\"title\":\"Revenue (USD)\",\"type\":\"number\",\"format\":\"double\",\"x-ms-permission\":\"read-write\",\"x-ms-sort\":\"asc,desc\",\"x-ms-capabilities\":{\"filterFunctions\":[\"eq\",\"gt\",\"ge\",\"lt\",\"le\",\"ne\"]},\"maximum\":1.7976931348623157e+308,\"minimum\":-1.7976931348623157e+308},\"OData__ColorTag\":{\"title\":\"Color Tag\",\"type\":\"string\",\"x-ms-permission\":\"read-only\",\"x-ms-sort\":\"asc,desc\",\"x-ms-capabilities\":{\"filterFunctions\":[\"eq\",\"startswith\"]},\"maxLength\":255},\"ComplianceAssetId\":{\"title\":\"Compliance Asset Id\",\"type\":\"string\",\"x-ms-permission\":\"read-only\",\"x-ms-sort\":\"asc,desc\",\"x-ms-capabilities\":{\"filterFunctions\":[\"eq\",\"startswith\"]},\"maxLength\":255},\"Modified\":{\"title\":\"Modified\",\"description\":\"When this item was last changed.\",\"type\":\"string\",\"format\":\"date-time\",\"x-ms-permission\":\"read-only\",\"x-ms-sort\":\"asc,desc\",\"x-ms-capabilities\":{\"filterFunctions\":[\"eq\",\"gt\",\"ge\",\"lt\",\"le\",\"ne\"]}},\"Created\":{\"title\":\"Created\",\"description\":\"When this item was created.\",\"type\":\"string\",\"format\":\"date-time\",\"x-ms-permission\":\"read-only\",\"x-ms-sort\":\"asc,desc\",\"x-ms-capabilities\":{\"filterFunctions\":[\"eq\",\"gt\",\"ge\",\"lt\",\"le\",\"ne\"]}},\"Author#Claims\":{\"title\":\"Created By Claims\",\"type\":\"string\",\"description\":\"Internal identifier for the user who created this item.\",\"x-ms-permission\":\"read-only\",\"x-ms-visibility\":\"internal\"},\"Author\":{\"title\":\"Created By\",\"description\":\"The user who created this item.\",\"type\":\"object\",\"x-ms-permission\":\"read-only\",\"x-ms-sort\":\"asc,desc\",\"x-ms-capabilities\":{\"filterFunctions\":[\"eq\"]},\"properties\":{\"@odata.type\":{\"title\":\"@odata.type\",\"x-ms-visibility\":\"internal\",\"type\":\"string\",\"x-ms-permission\":\"read-only\"},\"Claims\":{\"title\":\"Claims\",\"type\":\"string\",\"description\":\"Internal identifier for the user who created this item.\",\"x-ms-permission\":\"read-only\",\"x-ms-dynamic-values\":{\"operationId\":\"GetEntityValues\",\"parameters\":{\"dataset\":{\"parameter\":\"dataset\"},\"table\":{\"parameter\":\"table\"},\"id\":\"1df5e554-ec7e-46a6-901d-d85a3881cb18\"},\"value-path\":\"Claims\",\"value-title\":\"DisplayName\",\"value-collection\":\"value\"}},\"DisplayName\":{\"title\":\"DisplayName\",\"type\":\"string\",\"description\":\"The name of the user who created this item.\",\"x-ms-permission\":\"read-only\",\"x-ms-capabilities\":{\"x-ms-sp\":{\"OdataQueryName\":\"Title\"},\"filterFunctions\":[\"eq\",\"startswith\"]}},\"Email\":{\"title\":\"Email\",\"type\":\"string\",\"description\":\"Email address of the user who created this item.\",\"format\":\"email\",\"x-ms-permission\":\"read-only\",\"x-ms-capabilities\":{\"x-ms-sp\":{\"OdataQueryName\":\"EMail\"},\"filterFunctions\":[\"eq\",\"startswith\"]}},\"Picture\":{\"title\":\"Picture\",\"type\":\"string\",\"description\":\"Link to a picture of the user who created this item.\",\"format\":\"uri\",\"x-ms-media-kind\":\"image\",\"x-ms-media-default-folder-path\":\"/personal/ashutoshupadhyay_codeneraprivatelimited_onmicrosoft_com\",\"x-ms-media-base-url\":\"https://codeneraprivatelimited-my.sharepoint.com/personal/ashutoshupadhyay_codeneraprivatelimited_onmicrosoft_com\",\"x-ms-permission\":\"read-only\"},\"Department\":{\"title\":\"Department\",\"type\":\"string\",\"description\":\"Department name of the user who created this item.\",\"x-ms-permission\":\"read-only\"},\"JobTitle\":{\"title\":\"JobTitle\",\"type\":\"string\",\"description\":\"Job title of the user who created this item.\",\"x-ms-permission\":\"read-only\"}},\"x-ms-displayFormat\":{\"titleProperty\":\"DisplayName\",\"subtitleProperty\":\"Email\",\"thumbnailProperty\":\"Picture\"}},\"Editor#Claims\":{\"title\":\"Modified By Claims\",\"type\":\"string\",\"description\":\"Internal identifier for the user who last changed this item.\",\"x-ms-permission\":\"read-only\",\"x-ms-visibility\":\"internal\"},\"Editor\":{\"title\":\"Modified By\",\"description\":\"The user who last changed this item.\",\"type\":\"object\",\"x-ms-permission\":\"read-only\",\"x-ms-sort\":\"asc,desc\",\"x-ms-capabilities\":{\"filterFunctions\":[\"eq\"]},\"properties\":{\"@odata.type\":{\"title\":\"@odata.type\",\"x-ms-visibility\":\"internal\",\"type\":\"string\",\"x-ms-permission\":\"read-only\"},\"Claims\":{\"title\":\"Claims\",\"type\":\"string\",\"description\":\"Internal identifier for the user who last changed this item.\",\"x-ms-permission\":\"read-only\",\"x-ms-dynamic-values\":{\"operationId\":\"GetEntityValues\",\"parameters\":{\"dataset\":{\"parameter\":\"dataset\"},\"table\":{\"parameter\":\"table\"},\"id\":\"d31655d1-1d5b-4511-95a1-7a09e9b75bf2\"},\"value-path\":\"Claims\",\"value-title\":\"DisplayName\",\"value-collection\":\"value\"}},\"DisplayName\":{\"title\":\"DisplayName\",\"type\":\"string\",\"description\":\"The name of the user who last changed this item.\",\"x-ms-permission\":\"read-only\",\"x-ms-capabilities\":{\"x-ms-sp\":{\"OdataQueryName\":\"Title\"},\"filterFunctions\":[\"eq\",\"startswith\"]}},\"Email\":{\"title\":\"Email\",\"type\":\"string\",\"description\":\"Email address of the user who last changed this item.\",\"format\":\"email\",\"x-ms-permission\":\"read-only\",\"x-ms-capabilities\":{\"x-ms-sp\":{\"OdataQueryName\":\"EMail\"},\"filterFunctions\":[\"eq\",\"startswith\"]}},\"Picture\":{\"title\":\"Picture\",\"type\":\"string\",\"description\":\"Link to a picture of the user who last changed this item.\",\"format\":\"uri\",\"x-ms-media-kind\":\"image\",\"x-ms-media-default-folder-path\":\"/personal/ashutoshupadhyay_codeneraprivatelimited_onmicrosoft_com\",\"x-ms-media-base-url\":\"https://codeneraprivatelimited-my.sharepoint.com/personal/ashutoshupadhyay_codeneraprivatelimited_onmicrosoft_com\",\"x-ms-permission\":\"read-only\"},\"Department\":{\"title\":\"Department\",\"type\":\"string\",\"description\":\"Department name of the user who last changed this item.\",\"x-ms-permission\":\"read-only\"},\"JobTitle\":{\"title\":\"JobTitle\",\"type\":\"string\",\"description\":\"Job title of the user who last changed this item.\",\"x-ms-permission\":\"read-only\"}},\"x-ms-displayFormat\":{\"titleProperty\":\"DisplayName\",\"subtitleProperty\":\"Email\",\"thumbnailProperty\":\"Picture\"}},\"{Identifier}\":{\"title\":\"Identifier\",\"description\":\"Value that can be used in file related actions for selecting a file.\",\"type\":\"string\",\"x-ms-permission\":\"read-only\",\"x-ms-sort\":\"none\"},\"{IsFolder}\":{\"title\":\"IsFolder\",\"description\":\"True when the item is a folder, false otherwise.\",\"type\":\"boolean\",\"x-ms-permission\":\"read-only\",\"x-ms-sort\":\"none\"},\"{Thumbnail}\":{\"title\":\"Thumbnail\",\"description\":\"URL to the thumbnails of the item in 3 different sizes, if available.\",\"type\":\"object\",\"x-ms-permission\":\"read-only\",\"x-ms-sort\":\"none\",\"properties\":{\"@odata.type\":{\"title\":\"@odata.type\",\"x-ms-visibility\":\"internal\",\"type\":\"string\",\"x-ms-permission\":\"read-only\"},\"Small\":{\"title\":\"Small\",\"type\":\"string\",\"description\":\"URL to the small, highly compressed size thumbnail of the item, if available.\",\"x-ms-permission\":\"read-only\"},\"Medium\":{\"title\":\"Medium\",\"type\":\"string\",\"description\":\"URL to the standard size thumbnail of the item, if available.\",\"x-ms-permission\":\"read-only\"},\"Large\":{\"title\":\"Large\",\"type\":\"string\",\"description\":\"URL to the largest size thumbnail of the item, if available.\",\"x-ms-permission\":\"read-only\"}}},\"{Link}\":{\"title\":\"Link to item\",\"description\":\"Link that can be used to get to the file or list item. Only people with permissions to the item will be able to open the link.\",\"type\":\"string\",\"x-ms-permission\":\"read-only\",\"x-ms-sort\":\"none\"},\"{Name}\":{\"title\":\"Name\",\"description\":\"File name of the item in document libraries, display name of the item in lists.\",\"type\":\"string\",\"x-ms-permission\":\"read-only\",\"x-ms-sort\":\"none\"},\"{FilenameWithExtension}\":{\"title\":\"File name with extension\",\"description\":\"For libraries, returns file name including extension. For lists, returns the title property.\",\"type\":\"string\",\"x-ms-permission\":\"read-only\",\"x-ms-sort\":\"none\"},\"{Path}\":{\"title\":\"Folder path\",\"description\":\"Path to the folder the item is in, relative to the site address.\",\"type\":\"string\",\"x-ms-permission\":\"read-only\",\"x-ms-sort\":\"none\"},\"{FullPath}\":{\"title\":\"Full Path\",\"description\":\"Full path of an item or a folder or a file\",\"type\":\"string\",\"x-ms-permission\":\"read-only\",\"x-ms-sort\":\"none\"},\"{ModerationStatus}\":{\"title\":\"Content approval status\",\"description\":\"The content approval status. It can be one of the following: Draft, Pending, Approved, or Rejected\",\"type\":\"string\",\"x-ms-permission\":\"read-only\",\"x-ms-sort\":\"none\"},\"{ModerationComment}\":{\"title\":\"Comments associated with the content approval of this list item\",\"description\":\"The comments associated with moderation of the list item.\",\"type\":\"string\",\"x-ms-permission\":\"read-only\",\"x-ms-sort\":\"none\"},\"{HasAttachments}\":{\"title\":\"Has attachments\",\"description\":\"Indicates the presence of attachments in the item.\",\"type\":\"boolean\",\"x-ms-permission\":\"read-only\",\"x-ms-sort\":\"none\"},\"{Attachments}@odata.type\":{\"title\":\"{Attachments}\",\"type\":\"string\",\"x-ms-visibility\":\"internal\",\"x-ms-permission\":\"read-write\"},\"{Attachments}\":{\"title\":\"Attachments\",\"description\":\"Never returns any data. Use Attachment endpoints to access item attachments.\",\"x-ms-permission\":\"read-write\",\"targetEntity\":\"attachments\",\"format\":\"x-ms-containedMediaEntity\",\"x-ms-visibility\":\"internal\",\"type\":\"array\",\"items\":{\"type\":\"object\",\"format\":\"x-ms-mediaEntity\",\"x-ms-sort\":\"none\",\"properties\":{\"@odata.type\":{\"title\":\"@odata.type\",\"x-ms-visibility\":\"internal\",\"type\":\"string\",\"x-ms-permission\":\"read-write\"},\"Id\":{\"title\":\"Id\",\"type\":\"string\",\"x-ms-keyType\":\"primary\",\"x-ms-keyOrder\":1,\"x-ms-permission\":\"read-only\"},\"AbsoluteUri\":{\"title\":\"AbsoluteUri\",\"type\":\"string\",\"format\":\"uri\",\"x-ms-permission\":\"read-only\"},\"DisplayName\":{\"title\":\"DisplayName\",\"type\":\"string\",\"x-ms-permission\":\"read-only\"}}},\"@odata.type\":\"#Collection(Microsoft.Azure.Connectors.SharePoint.SPListItemAttachment)\"},\"{VersionNumber}\":{\"title\":\"Version number\",\"description\":\"The version number of the file or the list item.\",\"type\":\"string\",\"x-ms-permission\":\"read-only\",\"x-ms-sort\":\"none\"},\"{TriggerWindowStartToken}\":{\"title\":\"Trigger Window Start Token\",\"description\":\"A token expressing the time of the last flow check. Use this if you want to check if one or more columns were modified since the last flow check.\",\"type\":\"string\",\"x-ms-permission\":\"read-only\",\"x-ms-sort\":\"none\"},\"{TriggerWindowEndToken}\":{\"title\":\"Trigger Window End Token\",\"description\":\"A token expressing the time of the current flow check. Use this if you want to check if one or more columns were modified since the last flow check.\",\"type\":\"string\",\"x-ms-permission\":\"read-only\",\"x-ms-sort\":\"none\"}},\"x-ms-relationships\":{\"Author\":{\"targetEntity\":\"Author\",\"referentialConstraints\":{\"Author#Claims\":{\"referencedProperty\":\"Claims\"}}},\"Editor\":{\"targetEntity\":\"Editor\",\"referentialConstraints\":{\"Editor#Claims\":{\"referencedProperty\":\"Claims\"}}}},\"x-ms-displayFormat\":{\"propertiesDisplayOrder\":[\"Title\",\"Country\",\"SalesReps\",\"FirstName\",\"LastName\",\"Gender\",\"Age\",\"RankLevels\",\"Rank\",\"Products\",\"Years\",\"Quarter\",\"Month\",\"Revenue_x0028_USD_x0029_\",\"{Attachments}\"],\"propertiesCompactDisplayOrder\":[\"Title\",\"Country\",\"SalesReps\",\"FirstName\",\"LastName\",\"Gender\",\"Age\",\"RankLevels\",\"Rank\",\"Products\",\"Years\",\"Quarter\",\"Month\",\"Revenue_x0028_USD_x0029_\"],\"propertiesTabularDisplayOrder\":[\"Title\",\"Country\",\"SalesReps\",\"FirstName\",\"LastName\",\"Gender\",\"Age\",\"RankLevels\",\"Rank\",\"Products\",\"Years\",\"Quarter\",\"Month\",\"Revenue_x0028_USD_x0029_\"]}}},\"referencedEntities\":{\"Author\":{\"lookupEndpoint\":{\"path\":\"/tables/e779dc0e-3c16-4d9e-b409-377f8a47598e/entities/Author\",\"capabilities\":{\"searchable\":true,\"requiresSearch\":false}}},\"Editor\":{\"lookupEndpoint\":{\"path\":\"/tables/e779dc0e-3c16-4d9e-b409-377f8a47598e/entities/Editor\",\"capabilities\":{\"searchable\":true,\"requiresSearch\":false}}}},\"webUrl\":\"https://codeneraprivatelimited-my.sharepoint.com/personal/ashutoshupadhyay_codeneraprivatelimited_onmicrosoft_com/Lists/Suyog Financial Performance/AllItems.aspx\"}"
      },
      "ConnectedDataSourceInfoNameMapping": {
        "Title": "Title",
        "SalesReps": "Sales Reps",
        "Gender": "Gender",
        "{TriggerWindowEndToken}": "Trigger Window End Token",
        "Month": "Month",
        "{Link}": "Link to item",
        "LastName": "Last Name",
        "ComplianceAssetId": "Compliance Asset Id",
        "Editor": "Modified By",
        "{Attachments}@odata.type": "{Attachments} ({Attachments}@odata.type)",
        "FirstName": "First Name",
        "Editor#Claims": "Modified By Claims",
        "{IsFolder}": "IsFolder",
        "{VersionNumber}": "Version number",
        "Products": "Products",
        "Rank": "Rank",
        "{Thumbnail}": "Thumbnail",
        "{Path}": "Folder path",
        "{FilenameWithExtension}": "File name with extension",
        "{ModerationStatus}": "Content approval status",
        "RankLevels": "Rank Levels",
        "Quarter": "Quarter",
        "{Identifier}": "Identifier",
        "OData__ColorTag": "Color Tag",
        "Author": "Created By",
        "{FullPath}": "Full Path",
        "Age": "Age",
        "{Attachments}": "Attachments",
        "{HasAttachments}": "Has attachments",
        "Revenue_x0028_USD_x0029_": "Revenue (USD)",
        "Author#Claims": "Created By Claims",
        "Created": "Created",
        "ID": "ID",
        "{ModerationComment}": "Comments associated with the content approval of this list item",
        "Years": "Years",
        "Country": "Country",
        "Modified": "Modified",
        "{TriggerWindowStartToken}": "Trigger Window Start Token",
        "{Name}": "Name"
      }
    },
    {
      "Name": "Userpass_Finance",
      "IsSampleData": false,
      "IsWritable": true,
      "Type": "ConnectedDataSourceInfo",
      "DatasetName": "https://codeneraprivatelimited-my.sharepoint.com/personal/ashutoshupadhyay_codeneraprivatelimited_onmicrosoft_com",
      "TableName": "65e5ad9e-c017-4841-8a1c-7bd5a31cdd1d",
      "ApiId": "/providers/microsoft.powerapps/apis/shared_sharepointonline",
      "EncodeDataset": true,
      "CdpRevision": {
        "RevisionNumber": 1,
        "BaseUrl": "/",
        "LastChangedTimeString": "2024-02-08T17:53:32.2760000Z"
      },
      "DataEntityMetadataJson": {
        "65e5ad9e-c017-4841-8a1c-7bd5a31cdd1d": "{\"name\":\"65e5ad9e-c017-4841-8a1c-7bd5a31cdd1d\",\"title\":\"Userpass_Finance\",\"x-ms-permission\":\"read-write\",\"x-ms-capabilities\":{\"sortRestrictions\":{\"sortable\":true,\"unsortableProperties\":[\"{Identifier}\",\"{IsFolder}\",\"{Thumbnail}\",\"{Link}\",\"{Name}\",\"{FilenameWithExtension}\",\"{Path}\",\"{FullPath}\",\"{ModerationStatus}\",\"{ModerationComment}\",\"{HasAttachments}\",\"{Attachments}\",\"{VersionNumber}\",\"{TriggerWindowStartToken}\",\"{TriggerWindowEndToken}\"]},\"filterRestrictions\":{\"filterable\":true,\"nonFilterableProperties\":[\"{Identifier}\",\"{IsFolder}\",\"{Thumbnail}\",\"{Link}\",\"{Name}\",\"{FilenameWithExtension}\",\"{Path}\",\"{FullPath}\",\"{ModerationStatus}\",\"{ModerationComment}\",\"{HasAttachments}\",\"{Attachments}\",\"{VersionNumber}\",\"{TriggerWindowStartToken}\",\"{TriggerWindowEndToken}\"]},\"isOnlyServerPagable\":true,\"filterFunctionSupport\":[\"and\",\"or\",\"eq\",\"startswith\",\"gt\",\"ge\",\"lt\",\"le\",\"ne\"],\"serverPagingOptions\":[\"top\",\"skiptoken\"],\"odataVersion\":3},\"schema\":{\"type\":\"array\",\"items\":{\"type\":\"object\",\"required\":[],\"properties\":{\"ID\":{\"title\":\"ID\",\"description\":\"List item id. Use this value for specifying the item to act on in other list related actions.\",\"type\":\"integer\",\"format\":\"int64\",\"x-ms-keyType\":\"primary\",\"x-ms-keyOrder\":1,\"x-ms-permission\":\"read-only\",\"x-ms-sort\":\"asc,desc\",\"x-ms-capabilities\":{\"filterFunctions\":[\"eq\"]}},\"Title\":{\"title\":\"Title\",\"type\":\"string\",\"x-ms-permission\":\"read-write\",\"x-ms-sort\":\"asc,desc\",\"x-ms-capabilities\":{\"filterFunctions\":[\"eq\",\"startswith\"]},\"maxLength\":255},\"Password\":{\"title\":\"Password\",\"type\":\"string\",\"x-ms-permission\":\"read-write\",\"x-ms-sort\":\"asc,desc\",\"x-ms-capabilities\":{\"filterFunctions\":[\"eq\",\"startswith\"]},\"maxLength\":255},\"OData__ColorTag\":{\"title\":\"Color Tag\",\"type\":\"string\",\"x-ms-permission\":\"read-only\",\"x-ms-sort\":\"asc,desc\",\"x-ms-capabilities\":{\"filterFunctions\":[\"eq\",\"startswith\"]},\"maxLength\":255},\"ComplianceAssetId\":{\"title\":\"Compliance Asset Id\",\"type\":\"string\",\"x-ms-permission\":\"read-only\",\"x-ms-sort\":\"asc,desc\",\"x-ms-capabilities\":{\"filterFunctions\":[\"eq\",\"startswith\"]},\"maxLength\":255},\"Modified\":{\"title\":\"Modified\",\"description\":\"When this item was last changed.\",\"type\":\"string\",\"format\":\"date-time\",\"x-ms-permission\":\"read-only\",\"x-ms-sort\":\"asc,desc\",\"x-ms-capabilities\":{\"filterFunctions\":[\"eq\",\"gt\",\"ge\",\"lt\",\"le\",\"ne\"]}},\"Created\":{\"title\":\"Created\",\"description\":\"When this item was created.\",\"type\":\"string\",\"format\":\"date-time\",\"x-ms-permission\":\"read-only\",\"x-ms-sort\":\"asc,desc\",\"x-ms-capabilities\":{\"filterFunctions\":[\"eq\",\"gt\",\"ge\",\"lt\",\"le\",\"ne\"]}},\"Author#Claims\":{\"title\":\"Created By Claims\",\"type\":\"string\",\"description\":\"Internal identifier for the user who created this item.\",\"x-ms-permission\":\"read-only\",\"x-ms-visibility\":\"internal\"},\"Author\":{\"title\":\"Created By\",\"description\":\"The user who created this item.\",\"type\":\"object\",\"x-ms-permission\":\"read-only\",\"x-ms-sort\":\"asc,desc\",\"x-ms-capabilities\":{\"filterFunctions\":[\"eq\"]},\"properties\":{\"@odata.type\":{\"title\":\"@odata.type\",\"x-ms-visibility\":\"internal\",\"type\":\"string\",\"x-ms-permission\":\"read-only\"},\"Claims\":{\"title\":\"Claims\",\"type\":\"string\",\"description\":\"Internal identifier for the user who created this item.\",\"x-ms-permission\":\"read-only\",\"x-ms-dynamic-values\":{\"operationId\":\"GetEntityValues\",\"parameters\":{\"dataset\":{\"parameter\":\"dataset\"},\"table\":{\"parameter\":\"table\"},\"id\":\"1df5e554-ec7e-46a6-901d-d85a3881cb18\"},\"value-path\":\"Claims\",\"value-title\":\"DisplayName\",\"value-collection\":\"value\"}},\"DisplayName\":{\"title\":\"DisplayName\",\"type\":\"string\",\"description\":\"The name of the user who created this item.\",\"x-ms-permission\":\"read-only\",\"x-ms-capabilities\":{\"x-ms-sp\":{\"OdataQueryName\":\"Title\"},\"filterFunctions\":[\"eq\",\"startswith\"]}},\"Email\":{\"title\":\"Email\",\"type\":\"string\",\"description\":\"Email address of the user who created this item.\",\"format\":\"email\",\"x-ms-permission\":\"read-only\",\"x-ms-capabilities\":{\"x-ms-sp\":{\"OdataQueryName\":\"EMail\"},\"filterFunctions\":[\"eq\",\"startswith\"]}},\"Picture\":{\"title\":\"Picture\",\"type\":\"string\",\"description\":\"Link to a picture of the user who created this item.\",\"format\":\"uri\",\"x-ms-media-kind\":\"image\",\"x-ms-media-default-folder-path\":\"/personal/ashutoshupadhyay_codeneraprivatelimited_onmicrosoft_com\",\"x-ms-media-base-url\":\"https://codeneraprivatelimited-my.sharepoint.com/personal/ashutoshupadhyay_codeneraprivatelimited_onmicrosoft_com\",\"x-ms-permission\":\"read-only\"},\"Department\":{\"title\":\"Department\",\"type\":\"string\",\"description\":\"Department name of the user who created this item.\",\"x-ms-permission\":\"read-only\"},\"JobTitle\":{\"title\":\"JobTitle\",\"type\":\"string\",\"description\":\"Job title of the user who created this item.\",\"x-ms-permission\":\"read-only\"}},\"x-ms-displayFormat\":{\"titleProperty\":\"DisplayName\",\"subtitleProperty\":\"Email\",\"thumbnailProperty\":\"Picture\"}},\"Editor#Claims\":{\"title\":\"Modified By Claims\",\"type\":\"string\",\"description\":\"Internal identifier for the user who last changed this item.\",\"x-ms-permission\":\"read-only\",\"x-ms-visibility\":\"internal\"},\"Editor\":{\"title\":\"Modified By\",\"description\":\"The user who last changed this item.\",\"type\":\"object\",\"x-ms-permission\":\"read-only\",\"x-ms-sort\":\"asc,desc\",\"x-ms-capabilities\":{\"filterFunctions\":[\"eq\"]},\"properties\":{\"@odata.type\":{\"title\":\"@odata.type\",\"x-ms-visibility\":\"internal\",\"type\":\"string\",\"x-ms-permission\":\"read-only\"},\"Claims\":{\"title\":\"Claims\",\"type\":\"string\",\"description\":\"Internal identifier for the user who last changed this item.\",\"x-ms-permission\":\"read-only\",\"x-ms-dynamic-values\":{\"operationId\":\"GetEntityValues\",\"parameters\":{\"dataset\":{\"parameter\":\"dataset\"},\"table\":{\"parameter\":\"table\"},\"id\":\"d31655d1-1d5b-4511-95a1-7a09e9b75bf2\"},\"value-path\":\"Claims\",\"value-title\":\"DisplayName\",\"value-collection\":\"value\"}},\"DisplayName\":{\"title\":\"DisplayName\",\"type\":\"string\",\"description\":\"The name of the user who last changed this item.\",\"x-ms-permission\":\"read-only\",\"x-ms-capabilities\":{\"x-ms-sp\":{\"OdataQueryName\":\"Title\"},\"filterFunctions\":[\"eq\",\"startswith\"]}},\"Email\":{\"title\":\"Email\",\"type\":\"string\",\"description\":\"Email address of the user who last changed this item.\",\"format\":\"email\",\"x-ms-permission\":\"read-only\",\"x-ms-capabilities\":{\"x-ms-sp\":{\"OdataQueryName\":\"EMail\"},\"filterFunctions\":[\"eq\",\"startswith\"]}},\"Picture\":{\"title\":\"Picture\",\"type\":\"string\",\"description\":\"Link to a picture of the user who last changed this item.\",\"format\":\"uri\",\"x-ms-media-kind\":\"image\",\"x-ms-media-default-folder-path\":\"/personal/ashutoshupadhyay_codeneraprivatelimited_onmicrosoft_com\",\"x-ms-media-base-url\":\"https://codeneraprivatelimited-my.sharepoint.com/personal/ashutoshupadhyay_codeneraprivatelimited_onmicrosoft_com\",\"x-ms-permission\":\"read-only\"},\"Department\":{\"title\":\"Department\",\"type\":\"string\",\"description\":\"Department name of the user who last changed this item.\",\"x-ms-permission\":\"read-only\"},\"JobTitle\":{\"title\":\"JobTitle\",\"type\":\"string\",\"description\":\"Job title of the user who last changed this item.\",\"x-ms-permission\":\"read-only\"}},\"x-ms-displayFormat\":{\"titleProperty\":\"DisplayName\",\"subtitleProperty\":\"Email\",\"thumbnailProperty\":\"Picture\"}},\"{Identifier}\":{\"title\":\"Identifier\",\"description\":\"Value that can be used in file related actions for selecting a file.\",\"type\":\"string\",\"x-ms-permission\":\"read-only\",\"x-ms-sort\":\"none\"},\"{IsFolder}\":{\"title\":\"IsFolder\",\"description\":\"True when the item is a folder, false otherwise.\",\"type\":\"boolean\",\"x-ms-permission\":\"read-only\",\"x-ms-sort\":\"none\"},\"{Thumbnail}\":{\"title\":\"Thumbnail\",\"description\":\"URL to the thumbnails of the item in 3 different sizes, if available.\",\"type\":\"object\",\"x-ms-permission\":\"read-only\",\"x-ms-sort\":\"none\",\"properties\":{\"@odata.type\":{\"title\":\"@odata.type\",\"x-ms-visibility\":\"internal\",\"type\":\"string\",\"x-ms-permission\":\"read-only\"},\"Small\":{\"title\":\"Small\",\"type\":\"string\",\"description\":\"URL to the small, highly compressed size thumbnail of the item, if available.\",\"x-ms-permission\":\"read-only\"},\"Medium\":{\"title\":\"Medium\",\"type\":\"string\",\"description\":\"URL to the standard size thumbnail of the item, if available.\",\"x-ms-permission\":\"read-only\"},\"Large\":{\"title\":\"Large\",\"type\":\"string\",\"description\":\"URL to the largest size thumbnail of the item, if available.\",\"x-ms-permission\":\"read-only\"}}},\"{Link}\":{\"title\":\"Link to item\",\"description\":\"Link that can be used to get to the file or list item. Only people with permissions to the item will be able to open the link.\",\"type\":\"string\",\"x-ms-permission\":\"read-only\",\"x-ms-sort\":\"none\"},\"{Name}\":{\"title\":\"Name\",\"description\":\"File name of the item in document libraries, display name of the item in lists.\",\"type\":\"string\",\"x-ms-permission\":\"read-only\",\"x-ms-sort\":\"none\"},\"{FilenameWithExtension}\":{\"title\":\"File name with extension\",\"description\":\"For libraries, returns file name including extension. For lists, returns the title property.\",\"type\":\"string\",\"x-ms-permission\":\"read-only\",\"x-ms-sort\":\"none\"},\"{Path}\":{\"title\":\"Folder path\",\"description\":\"Path to the folder the item is in, relative to the site address.\",\"type\":\"string\",\"x-ms-permission\":\"read-only\",\"x-ms-sort\":\"none\"},\"{FullPath}\":{\"title\":\"Full Path\",\"description\":\"Full path of an item or a folder or a file\",\"type\":\"string\",\"x-ms-permission\":\"read-only\",\"x-ms-sort\":\"none\"},\"{ModerationStatus}\":{\"title\":\"Content approval status\",\"description\":\"The content approval status. It can be one of the following: Draft, Pending, Approved, or Rejected\",\"type\":\"string\",\"x-ms-permission\":\"read-only\",\"x-ms-sort\":\"none\"},\"{ModerationComment}\":{\"title\":\"Comments associated with the content approval of this list item\",\"description\":\"The comments associated with moderation of the list item.\",\"type\":\"string\",\"x-ms-permission\":\"read-only\",\"x-ms-sort\":\"none\"},\"{HasAttachments}\":{\"title\":\"Has attachments\",\"description\":\"Indicates the presence of attachments in the item.\",\"type\":\"boolean\",\"x-ms-permission\":\"read-only\",\"x-ms-sort\":\"none\"},\"{Attachments}@odata.type\":{\"title\":\"{Attachments}\",\"type\":\"string\",\"x-ms-visibility\":\"internal\",\"x-ms-permission\":\"read-write\"},\"{Attachments}\":{\"title\":\"Attachments\",\"description\":\"Never returns any data. Use Attachment endpoints to access item attachments.\",\"x-ms-permission\":\"read-write\",\"targetEntity\":\"attachments\",\"format\":\"x-ms-containedMediaEntity\",\"x-ms-visibility\":\"internal\",\"type\":\"array\",\"items\":{\"type\":\"object\",\"format\":\"x-ms-mediaEntity\",\"x-ms-sort\":\"none\",\"properties\":{\"@odata.type\":{\"title\":\"@odata.type\",\"x-ms-visibility\":\"internal\",\"type\":\"string\",\"x-ms-permission\":\"read-write\"},\"Id\":{\"title\":\"Id\",\"type\":\"string\",\"x-ms-keyType\":\"primary\",\"x-ms-keyOrder\":1,\"x-ms-permission\":\"read-only\"},\"AbsoluteUri\":{\"title\":\"AbsoluteUri\",\"type\":\"string\",\"format\":\"uri\",\"x-ms-permission\":\"read-only\"},\"DisplayName\":{\"title\":\"DisplayName\",\"type\":\"string\",\"x-ms-permission\":\"read-only\"}}},\"@odata.type\":\"#Collection(Microsoft.Azure.Connectors.SharePoint.SPListItemAttachment)\"},\"{VersionNumber}\":{\"title\":\"Version number\",\"description\":\"The version number of the file or the list item.\",\"type\":\"string\",\"x-ms-permission\":\"read-only\",\"x-ms-sort\":\"none\"},\"{TriggerWindowStartToken}\":{\"title\":\"Trigger Window Start Token\",\"description\":\"A token expressing the time of the last flow check. Use this if you want to check if one or more columns were modified since the last flow check.\",\"type\":\"string\",\"x-ms-permission\":\"read-only\",\"x-ms-sort\":\"none\"},\"{TriggerWindowEndToken}\":{\"title\":\"Trigger Window End Token\",\"description\":\"A token expressing the time of the current flow check. Use this if you want to check if one or more columns were modified since the last flow check.\",\"type\":\"string\",\"x-ms-permission\":\"read-only\",\"x-ms-sort\":\"none\"}},\"x-ms-relationships\":{\"Author\":{\"targetEntity\":\"Author\",\"referentialConstraints\":{\"Author#Claims\":{\"referencedProperty\":\"Claims\"}}},\"Editor\":{\"targetEntity\":\"Editor\",\"referentialConstraints\":{\"Editor#Claims\":{\"referencedProperty\":\"Claims\"}}}},\"x-ms-displayFormat\":{\"propertiesDisplayOrder\":[\"Title\",\"Password\",\"{Attachments}\"],\"propertiesCompactDisplayOrder\":[\"Title\",\"Password\"],\"propertiesTabularDisplayOrder\":[\"Title\",\"Password\"]}}},\"referencedEntities\":{\"Author\":{\"lookupEndpoint\":{\"path\":\"/tables/65e5ad9e-c017-4841-8a1c-7bd5a31cdd1d/entities/Author\",\"capabilities\":{\"searchable\":true,\"requiresSearch\":false}}},\"Editor\":{\"lookupEndpoint\":{\"path\":\"/tables/65e5ad9e-c017-4841-8a1c-7bd5a31cdd1d/entities/Editor\",\"capabilities\":{\"searchable\":true,\"requiresSearch\":false}}}},\"webUrl\":\"https://codeneraprivatelimited-my.sharepoint.com/personal/ashutoshupadhyay_codeneraprivatelimited_onmicrosoft_com/Lists/Userpass_Finance/AllItems.aspx\"}"
      },
      "ConnectedDataSourceInfoNameMapping": {
        "{Link}": "Link to item",
        "Editor": "Modified By",
        "{VersionNumber}": "Version number",
        "{Attachments}@odata.type": "{Attachments} ({Attachments}@odata.type)",
        "{Thumbnail}": "Thumbnail",
        "{Identifier}": "Identifier",
        "ComplianceAssetId": "Compliance Asset Id",
        "{Attachments}": "Attachments",
        "{FilenameWithExtension}": "File name with extension",
        "Title": "Title",
        "OData__ColorTag": "Color Tag",
        "{ModerationComment}": "Comments associated with the content approval of this list item",
        "Modified": "Modified",
        "{Name}": "Name",
        "Author#Claims": "Created By Claims",
        "ID": "ID",
        "Author": "Created By",
        "{TriggerWindowEndToken}": "Trigger Window End Token",
        "{FullPath}": "Full Path",
        "Password": "Password",
        "{TriggerWindowStartToken}": "Trigger Window Start Token",
        "{Path}": "Folder path",
        "Editor#Claims": "Modified By Claims",
        "{IsFolder}": "IsFolder",
        "Created": "Created",
        "{ModerationStatus}": "Content approval status",
        "{HasAttachments}": "Has attachments"
      }
    },
    {
      "Name": "Userpass_Finance_1",
      "IsSampleData": false,
      "IsWritable": true,
      "Type": "ConnectedDataSourceInfo",
      "DatasetName": "https://codeneraprivatelimited-my.sharepoint.com/personal/ashutoshupadhyay_codeneraprivatelimited_onmicrosoft_com",
      "TableName": "65e5ad9e-c017-4841-8a1c-7bd5a31cdd1d",
      "ApiId": "/providers/microsoft.powerapps/apis/shared_sharepointonline",
      "EncodeDataset": true,
      "CdpRevision": {
        "RevisionNumber": 1,
        "BaseUrl": "/",
        "LastChangedTimeString": "2024-02-08T17:53:32.2760000Z"
      },
      "DataEntityMetadataJson": {
        "65e5ad9e-c017-4841-8a1c-7bd5a31cdd1d": "{\"name\":\"65e5ad9e-c017-4841-8a1c-7bd5a31cdd1d\",\"title\":\"Userpass_Finance\",\"x-ms-permission\":\"read-write\",\"x-ms-capabilities\":{\"sortRestrictions\":{\"sortable\":true,\"unsortableProperties\":[\"{Identifier}\",\"{IsFolder}\",\"{Thumbnail}\",\"{Link}\",\"{Name}\",\"{FilenameWithExtension}\",\"{Path}\",\"{FullPath}\",\"{ModerationStatus}\",\"{ModerationComment}\",\"{HasAttachments}\",\"{Attachments}\",\"{VersionNumber}\",\"{TriggerWindowStartToken}\",\"{TriggerWindowEndToken}\"]},\"filterRestrictions\":{\"filterable\":true,\"nonFilterableProperties\":[\"{Identifier}\",\"{IsFolder}\",\"{Thumbnail}\",\"{Link}\",\"{Name}\",\"{FilenameWithExtension}\",\"{Path}\",\"{FullPath}\",\"{ModerationStatus}\",\"{ModerationComment}\",\"{HasAttachments}\",\"{Attachments}\",\"{VersionNumber}\",\"{TriggerWindowStartToken}\",\"{TriggerWindowEndToken}\"]},\"isOnlyServerPagable\":true,\"filterFunctionSupport\":[\"and\",\"or\",\"eq\",\"startswith\",\"gt\",\"ge\",\"lt\",\"le\",\"ne\"],\"serverPagingOptions\":[\"top\",\"skiptoken\"],\"odataVersion\":3},\"schema\":{\"type\":\"array\",\"items\":{\"type\":\"object\",\"required\":[],\"properties\":{\"ID\":{\"title\":\"ID\",\"description\":\"List item id. Use this value for specifying the item to act on in other list related actions.\",\"type\":\"integer\",\"format\":\"int64\",\"x-ms-keyType\":\"primary\",\"x-ms-keyOrder\":1,\"x-ms-permission\":\"read-only\",\"x-ms-sort\":\"asc,desc\",\"x-ms-capabilities\":{\"filterFunctions\":[\"eq\"]}},\"Title\":{\"title\":\"Title\",\"type\":\"string\",\"x-ms-permission\":\"read-write\",\"x-ms-sort\":\"asc,desc\",\"x-ms-capabilities\":{\"filterFunctions\":[\"eq\",\"startswith\"]},\"maxLength\":255},\"Password\":{\"title\":\"Password\",\"type\":\"string\",\"x-ms-permission\":\"read-write\",\"x-ms-sort\":\"asc,desc\",\"x-ms-capabilities\":{\"filterFunctions\":[\"eq\",\"startswith\"]},\"maxLength\":255},\"OData__ColorTag\":{\"title\":\"Color Tag\",\"type\":\"string\",\"x-ms-permission\":\"read-only\",\"x-ms-sort\":\"asc,desc\",\"x-ms-capabilities\":{\"filterFunctions\":[\"eq\",\"startswith\"]},\"maxLength\":255},\"ComplianceAssetId\":{\"title\":\"Compliance Asset Id\",\"type\":\"string\",\"x-ms-permission\":\"read-only\",\"x-ms-sort\":\"asc,desc\",\"x-ms-capabilities\":{\"filterFunctions\":[\"eq\",\"startswith\"]},\"maxLength\":255},\"Modified\":{\"title\":\"Modified\",\"description\":\"When this item was last changed.\",\"type\":\"string\",\"format\":\"date-time\",\"x-ms-permission\":\"read-only\",\"x-ms-sort\":\"asc,desc\",\"x-ms-capabilities\":{\"filterFunctions\":[\"eq\",\"gt\",\"ge\",\"lt\",\"le\",\"ne\"]}},\"Created\":{\"title\":\"Created\",\"description\":\"When this item was created.\",\"type\":\"string\",\"format\":\"date-time\",\"x-ms-permission\":\"read-only\",\"x-ms-sort\":\"asc,desc\",\"x-ms-capabilities\":{\"filterFunctions\":[\"eq\",\"gt\",\"ge\",\"lt\",\"le\",\"ne\"]}},\"Author#Claims\":{\"title\":\"Created By Claims\",\"type\":\"string\",\"description\":\"Internal identifier for the user who created this item.\",\"x-ms-permission\":\"read-only\",\"x-ms-visibility\":\"internal\"},\"Author\":{\"title\":\"Created By\",\"description\":\"The user who created this item.\",\"type\":\"object\",\"x-ms-permission\":\"read-only\",\"x-ms-sort\":\"asc,desc\",\"x-ms-capabilities\":{\"filterFunctions\":[\"eq\"]},\"properties\":{\"@odata.type\":{\"title\":\"@odata.type\",\"x-ms-visibility\":\"internal\",\"type\":\"string\",\"x-ms-permission\":\"read-only\"},\"Claims\":{\"title\":\"Claims\",\"type\":\"string\",\"description\":\"Internal identifier for the user who created this item.\",\"x-ms-permission\":\"read-only\",\"x-ms-dynamic-values\":{\"operationId\":\"GetEntityValues\",\"parameters\":{\"dataset\":{\"parameter\":\"dataset\"},\"table\":{\"parameter\":\"table\"},\"id\":\"1df5e554-ec7e-46a6-901d-d85a3881cb18\"},\"value-path\":\"Claims\",\"value-title\":\"DisplayName\",\"value-collection\":\"value\"}},\"DisplayName\":{\"title\":\"DisplayName\",\"type\":\"string\",\"description\":\"The name of the user who created this item.\",\"x-ms-permission\":\"read-only\",\"x-ms-capabilities\":{\"x-ms-sp\":{\"OdataQueryName\":\"Title\"},\"filterFunctions\":[\"eq\",\"startswith\"]}},\"Email\":{\"title\":\"Email\",\"type\":\"string\",\"description\":\"Email address of the user who created this item.\",\"format\":\"email\",\"x-ms-permission\":\"read-only\",\"x-ms-capabilities\":{\"x-ms-sp\":{\"OdataQueryName\":\"EMail\"},\"filterFunctions\":[\"eq\",\"startswith\"]}},\"Picture\":{\"title\":\"Picture\",\"type\":\"string\",\"description\":\"Link to a picture of the user who created this item.\",\"format\":\"uri\",\"x-ms-media-kind\":\"image\",\"x-ms-media-default-folder-path\":\"/personal/ashutoshupadhyay_codeneraprivatelimited_onmicrosoft_com\",\"x-ms-media-base-url\":\"https://codeneraprivatelimited-my.sharepoint.com/personal/ashutoshupadhyay_codeneraprivatelimited_onmicrosoft_com\",\"x-ms-permission\":\"read-only\"},\"Department\":{\"title\":\"Department\",\"type\":\"string\",\"description\":\"Department name of the user who created this item.\",\"x-ms-permission\":\"read-only\"},\"JobTitle\":{\"title\":\"JobTitle\",\"type\":\"string\",\"description\":\"Job title of the user who created this item.\",\"x-ms-permission\":\"read-only\"}},\"x-ms-displayFormat\":{\"titleProperty\":\"DisplayName\",\"subtitleProperty\":\"Email\",\"thumbnailProperty\":\"Picture\"}},\"Editor#Claims\":{\"title\":\"Modified By Claims\",\"type\":\"string\",\"description\":\"Internal identifier for the user who last changed this item.\",\"x-ms-permission\":\"read-only\",\"x-ms-visibility\":\"internal\"},\"Editor\":{\"title\":\"Modified By\",\"description\":\"The user who last changed this item.\",\"type\":\"object\",\"x-ms-permission\":\"read-only\",\"x-ms-sort\":\"asc,desc\",\"x-ms-capabilities\":{\"filterFunctions\":[\"eq\"]},\"properties\":{\"@odata.type\":{\"title\":\"@odata.type\",\"x-ms-visibility\":\"internal\",\"type\":\"string\",\"x-ms-permission\":\"read-only\"},\"Claims\":{\"title\":\"Claims\",\"type\":\"string\",\"description\":\"Internal identifier for the user who last changed this item.\",\"x-ms-permission\":\"read-only\",\"x-ms-dynamic-values\":{\"operationId\":\"GetEntityValues\",\"parameters\":{\"dataset\":{\"parameter\":\"dataset\"},\"table\":{\"parameter\":\"table\"},\"id\":\"d31655d1-1d5b-4511-95a1-7a09e9b75bf2\"},\"value-path\":\"Claims\",\"value-title\":\"DisplayName\",\"value-collection\":\"value\"}},\"DisplayName\":{\"title\":\"DisplayName\",\"type\":\"string\",\"description\":\"The name of the user who last changed this item.\",\"x-ms-permission\":\"read-only\",\"x-ms-capabilities\":{\"x-ms-sp\":{\"OdataQueryName\":\"Title\"},\"filterFunctions\":[\"eq\",\"startswith\"]}},\"Email\":{\"title\":\"Email\",\"type\":\"string\",\"description\":\"Email address of the user who last changed this item.\",\"format\":\"email\",\"x-ms-permission\":\"read-only\",\"x-ms-capabilities\":{\"x-ms-sp\":{\"OdataQueryName\":\"EMail\"},\"filterFunctions\":[\"eq\",\"startswith\"]}},\"Picture\":{\"title\":\"Picture\",\"type\":\"string\",\"description\":\"Link to a picture of the user who last changed this item.\",\"format\":\"uri\",\"x-ms-media-kind\":\"image\",\"x-ms-media-default-folder-path\":\"/personal/ashutoshupadhyay_codeneraprivatelimited_onmicrosoft_com\",\"x-ms-media-base-url\":\"https://codeneraprivatelimited-my.sharepoint.com/personal/ashutoshupadhyay_codeneraprivatelimited_onmicrosoft_com\",\"x-ms-permission\":\"read-only\"},\"Department\":{\"title\":\"Department\",\"type\":\"string\",\"description\":\"Department name of the user who last changed this item.\",\"x-ms-permission\":\"read-only\"},\"JobTitle\":{\"title\":\"JobTitle\",\"type\":\"string\",\"description\":\"Job title of the user who last changed this item.\",\"x-ms-permission\":\"read-only\"}},\"x-ms-displayFormat\":{\"titleProperty\":\"DisplayName\",\"subtitleProperty\":\"Email\",\"thumbnailProperty\":\"Picture\"}},\"{Identifier}\":{\"title\":\"Identifier\",\"description\":\"Value that can be used in file related actions for selecting a file.\",\"type\":\"string\",\"x-ms-permission\":\"read-only\",\"x-ms-sort\":\"none\"},\"{IsFolder}\":{\"title\":\"IsFolder\",\"description\":\"True when the item is a folder, false otherwise.\",\"type\":\"boolean\",\"x-ms-permission\":\"read-only\",\"x-ms-sort\":\"none\"},\"{Thumbnail}\":{\"title\":\"Thumbnail\",\"description\":\"URL to the thumbnails of the item in 3 different sizes, if available.\",\"type\":\"object\",\"x-ms-permission\":\"read-only\",\"x-ms-sort\":\"none\",\"properties\":{\"@odata.type\":{\"title\":\"@odata.type\",\"x-ms-visibility\":\"internal\",\"type\":\"string\",\"x-ms-permission\":\"read-only\"},\"Small\":{\"title\":\"Small\",\"type\":\"string\",\"description\":\"URL to the small, highly compressed size thumbnail of the item, if available.\",\"x-ms-permission\":\"read-only\"},\"Medium\":{\"title\":\"Medium\",\"type\":\"string\",\"description\":\"URL to the standard size thumbnail of the item, if available.\",\"x-ms-permission\":\"read-only\"},\"Large\":{\"title\":\"Large\",\"type\":\"string\",\"description\":\"URL to the largest size thumbnail of the item, if available.\",\"x-ms-permission\":\"read-only\"}}},\"{Link}\":{\"title\":\"Link to item\",\"description\":\"Link that can be used to get to the file or list item. Only people with permissions to the item will be able to open the link.\",\"type\":\"string\",\"x-ms-permission\":\"read-only\",\"x-ms-sort\":\"none\"},\"{Name}\":{\"title\":\"Name\",\"description\":\"File name of the item in document libraries, display name of the item in lists.\",\"type\":\"string\",\"x-ms-permission\":\"read-only\",\"x-ms-sort\":\"none\"},\"{FilenameWithExtension}\":{\"title\":\"File name with extension\",\"description\":\"For libraries, returns file name including extension. For lists, returns the title property.\",\"type\":\"string\",\"x-ms-permission\":\"read-only\",\"x-ms-sort\":\"none\"},\"{Path}\":{\"title\":\"Folder path\",\"description\":\"Path to the folder the item is in, relative to the site address.\",\"type\":\"string\",\"x-ms-permission\":\"read-only\",\"x-ms-sort\":\"none\"},\"{FullPath}\":{\"title\":\"Full Path\",\"description\":\"Full path of an item or a folder or a file\",\"type\":\"string\",\"x-ms-permission\":\"read-only\",\"x-ms-sort\":\"none\"},\"{ModerationStatus}\":{\"title\":\"Content approval status\",\"description\":\"The content approval status. It can be one of the following: Draft, Pending, Approved, or Rejected\",\"type\":\"string\",\"x-ms-permission\":\"read-only\",\"x-ms-sort\":\"none\"},\"{ModerationComment}\":{\"title\":\"Comments associated with the content approval of this list item\",\"description\":\"The comments associated with moderation of the list item.\",\"type\":\"string\",\"x-ms-permission\":\"read-only\",\"x-ms-sort\":\"none\"},\"{HasAttachments}\":{\"title\":\"Has attachments\",\"description\":\"Indicates the presence of attachments in the item.\",\"type\":\"boolean\",\"x-ms-permission\":\"read-only\",\"x-ms-sort\":\"none\"},\"{Attachments}@odata.type\":{\"title\":\"{Attachments}\",\"type\":\"string\",\"x-ms-visibility\":\"internal\",\"x-ms-permission\":\"read-write\"},\"{Attachments}\":{\"title\":\"Attachments\",\"description\":\"Never returns any data. Use Attachment endpoints to access item attachments.\",\"x-ms-permission\":\"read-write\",\"targetEntity\":\"attachments\",\"format\":\"x-ms-containedMediaEntity\",\"x-ms-visibility\":\"internal\",\"type\":\"array\",\"items\":{\"type\":\"object\",\"format\":\"x-ms-mediaEntity\",\"x-ms-sort\":\"none\",\"properties\":{\"@odata.type\":{\"title\":\"@odata.type\",\"x-ms-visibility\":\"internal\",\"type\":\"string\",\"x-ms-permission\":\"read-write\"},\"Id\":{\"title\":\"Id\",\"type\":\"string\",\"x-ms-keyType\":\"primary\",\"x-ms-keyOrder\":1,\"x-ms-permission\":\"read-only\"},\"AbsoluteUri\":{\"title\":\"AbsoluteUri\",\"type\":\"string\",\"format\":\"uri\",\"x-ms-permission\":\"read-only\"},\"DisplayName\":{\"title\":\"DisplayName\",\"type\":\"string\",\"x-ms-permission\":\"read-only\"}}},\"@odata.type\":\"#Collection(Microsoft.Azure.Connectors.SharePoint.SPListItemAttachment)\"},\"{VersionNumber}\":{\"title\":\"Version number\",\"description\":\"The version number of the file or the list item.\",\"type\":\"string\",\"x-ms-permission\":\"read-only\",\"x-ms-sort\":\"none\"},\"{TriggerWindowStartToken}\":{\"title\":\"Trigger Window Start Token\",\"description\":\"A token expressing the time of the last flow check. Use this if you want to check if one or more columns were modified since the last flow check.\",\"type\":\"string\",\"x-ms-permission\":\"read-only\",\"x-ms-sort\":\"none\"},\"{TriggerWindowEndToken}\":{\"title\":\"Trigger Window End Token\",\"description\":\"A token expressing the time of the current flow check. Use this if you want to check if one or more columns were modified since the last flow check.\",\"type\":\"string\",\"x-ms-permission\":\"read-only\",\"x-ms-sort\":\"none\"}},\"x-ms-relationships\":{\"Author\":{\"targetEntity\":\"Author\",\"referentialConstraints\":{\"Author#Claims\":{\"referencedProperty\":\"Claims\"}}},\"Editor\":{\"targetEntity\":\"Editor\",\"referentialConstraints\":{\"Editor#Claims\":{\"referencedProperty\":\"Claims\"}}}},\"x-ms-displayFormat\":{\"propertiesDisplayOrder\":[\"Title\",\"Password\",\"{Attachments}\"],\"propertiesCompactDisplayOrder\":[\"Title\",\"Password\"],\"propertiesTabularDisplayOrder\":[\"Title\",\"Password\"]}}},\"referencedEntities\":{\"Author\":{\"lookupEndpoint\":{\"path\":\"/tables/65e5ad9e-c017-4841-8a1c-7bd5a31cdd1d/entities/Author\",\"capabilities\":{\"searchable\":true,\"requiresSearch\":false}}},\"Editor\":{\"lookupEndpoint\":{\"path\":\"/tables/65e5ad9e-c017-4841-8a1c-7bd5a31cdd1d/entities/Editor\",\"capabilities\":{\"searchable\":true,\"requiresSearch\":false}}}},\"webUrl\":\"https://codeneraprivatelimited-my.sharepoint.com/personal/ashutoshupadhyay_codeneraprivatelimited_onmicrosoft_com/Lists/Userpass_Finance/AllItems.aspx\"}"
      },
      "ConnectedDataSourceInfoNameMapping": {
        "{TriggerWindowStartToken}": "Trigger Window Start Token",
        "Author": "Created By",
        "Editor": "Modified By",
        "{Path}": "Folder path",
        "{ModerationStatus}": "Content approval status",
        "{Name}": "Name",
        "Created": "Created",
        "Editor#Claims": "Modified By Claims",
        "{Attachments}": "Attachments",
        "OData__ColorTag": "Color Tag",
        "{Link}": "Link to item",
        "ComplianceAssetId": "Compliance Asset Id",
        "{FullPath}": "Full Path",
        "{TriggerWindowEndToken}": "Trigger Window End Token",
        "{IsFolder}": "IsFolder",
        "{Identifier}": "Identifier",
        "{VersionNumber}": "Version number",
        "Title": "Title",
        "{FilenameWithExtension}": "File name with extension",
        "{Attachments}@odata.type": "{Attachments} ({Attachments}@odata.type)",
        "{HasAttachments}": "Has attachments",
        "{Thumbnail}": "Thumbnail",
        "{ModerationComment}": "Comments associated with the content approval of this list item",
        "ID": "ID",
        "Modified": "Modified",
        "Password": "Password",
        "Author#Claims": "Created By Claims"
      }
    }
  ]
}